video_ql/__init__.py
video_ql/__main__.py
video_ql/base.py
video_ql/cli.py
video_ql/langchain_moondream.py
video_ql/models.py
video_ql/query.py
video_ql/query_proposer.py
video_ql/single_frame.py
video_ql/utils.py
video_ql/visualization.py
video_ql/yaml_analysis.py
video_ql-1.5.0.dist-info/licenses/LICENSE
video_ql-1.5.0.dist-info/METADATA
video_ql-1.5.0.dist-info/WHEEL
video_ql-1.5.0.dist-info/entry_points.txt
video_ql-1.5.0.dist-info/top_level.txt
video_ql-1.5.0.dist-info/RECORD
