Metadata-Version: 2.4
Name: video_ql
Version: 1.5.0
Summary: Searching through video data by asking the right questions
Home-page: https://github.com/AdityaNG/video_ql/
Author: AdityaNG
License-File: LICENSE
Requires-Dist: langchain[openai]
Requires-Dist: langchain[anthropic]
Requires-Dist: langchain-community
Requires-Dist: langchain-google-genai
Requires-Dist: opencv-python
Requires-Dist: pydantic
Requires-Dist: PyYAML
Requires-Dist: pillow
Requires-Dist: numpy
Requires-Dist: rich
Provides-Extra: test
Requires-Dist: pytest; extra == "test"
Requires-Dist: coverage; extra == "test"
Requires-Dist: flake8; extra == "test"
Requires-Dist: black; extra == "test"
Requires-Dist: isort; extra == "test"
Requires-Dist: pytest-cov; extra == "test"
Requires-Dist: mypy; extra == "test"
Requires-Dist: gitchangelog; extra == "test"
Requires-Dist: mkdocs; extra == "test"
Requires-Dist: lark; extra == "test"
Requires-Dist: types-requests; extra == "test"
Requires-Dist: requests-mock; extra == "test"
Requires-Dist: types-PyYAML; extra == "test"
Dynamic: author
Dynamic: description
Dynamic: description-content-type
Dynamic: home-page
Dynamic: license-file
Dynamic: provides-extra
Dynamic: requires-dist
Dynamic: summary
